jsonschema2dj/__init__.py
jsonschema2dj/fields.py
jsonschema2dj/meta-schema.json
jsonschema2dj/models.py
jsonschema2dj/relationships.py
jsonschema2dj/templates.py
jsonschema2dj/valdiators.py
jsonschema2dj/__pycache__/__init__.cpython-36.pyc
jsonschema2dj/__pycache__/__init__.cpython-38.pyc
jsonschema2dj/__pycache__/fields.cpython-36.pyc
jsonschema2dj/__pycache__/fields.cpython-38.pyc
jsonschema2dj/__pycache__/models.cpython-38.pyc
jsonschema2dj/__pycache__/relationships.cpython-36.pyc
jsonschema2dj/__pycache__/relationships.cpython-38.pyc
jsonschema2dj/__pycache__/templates.cpython-38.pyc
jsonschema2dj/__pycache__/valdiators.cpython-36.pyc
jsonschema2dj/__pycache__/valdiators.cpython-38.pyc
jsonschema2dj/management/__init__.py
jsonschema2dj/management/commands/__init__.py
jsonschema2dj/management/commands/jsonschema2dj.py
djangorestframework_jsonschema-0.1.0.dist-info/LICENSE
djangorestframework_jsonschema-0.1.0.dist-info/METADATA
djangorestframework_jsonschema-0.1.0.dist-info/WHEEL
djangorestframework_jsonschema-0.1.0.dist-info/top_level.txt
djangorestframework_jsonschema-0.1.0.dist-info/RECORD
