Metadata-Version: 2.1
Name: djangorestframework-jsonschema
Version: 0.1.0
Summary: build Django REST Framework API from jsonschema
Home-page: https://github.com/gecBurton/djangorestframework-jsonschema
Author: George Burton
Author-email: g.e.c.burton@gmail.com
License: BSD
Platform: UNKNOWN
Classifier: Development Status :: 2 - Pre-Alpha
Classifier: Environment :: Web Environment
Classifier: Framework :: Django
Classifier: Intended Audience :: Developers
Classifier: License :: OSI Approved :: BSD License
Classifier: Operating System :: OS Independent
Classifier: Natural Language :: English
Classifier: Programming Language :: Python :: 3
Classifier: Topic :: Internet :: WWW/HTTP
